LICENSE
setup.py
DrWatson/__init__.py
DrWatson.egg-info/PKG-INFO
DrWatson.egg-info/SOURCES.txt
DrWatson.egg-info/dependency_links.txt
DrWatson.egg-info/top_level.txt
drwatson/__init__.py
drwatson.egg-info/PKG-INFO
drwatson.egg-info/SOURCES.txt
drwatson.egg-info/dependency_links.txt
drwatson.egg-info/top_level.txt