Metadata-Version: 2.1
Name: drwatson
Version: 0.0.1
Summary: A scientific assistant inspired by the homonimous Julia package
Home-page: UNKNOWN
Author: Marco Vela
License: UNKNOWN
Platform: UNKNOWN
License-File: LICENSE
